ipfs_embeddings_py/__init__.py
ipfs_embeddings_py/chunker.py
ipfs_embeddings_py/elasticsearch_kit.py
ipfs_embeddings_py/elasticsearch_test.py
ipfs_embeddings_py/ipfs_embeddings.py
ipfs_embeddings_py/ipfs_multiformats.py
ipfs_embeddings_py/qdrant_kit copy.py
ipfs_embeddings_py/qdrant_kit.py
ipfs_embeddings_py/schema.py
ipfs_embeddings_py/temporary_file.py
ipfs_embeddings_py/test_ipfs_embeddings.py
ipfs_embeddings_py/typing_inspect.py
ipfs_embeddings_py/huggingface/__init__.py
ipfs_embeddings_py/huggingface/base.py
ipfs_embeddings_py/huggingface/pooling.py
ipfs_embeddings_py/huggingface/utils.py
ipfs_embeddings_py/node_parser/__init__.py
ipfs_embeddings_py/node_parser/interface.py
ipfs_embeddings_py/node_parser/loading.py
ipfs_embeddings_py/node_parser/node_utils.py
ipfs_embeddings_py/node_parser/file/__init__.py
ipfs_embeddings_py/node_parser/file/html.py
ipfs_embeddings_py/node_parser/file/json.py
ipfs_embeddings_py/node_parser/file/markdown.py
ipfs_embeddings_py/node_parser/file/simple_file.py
ipfs_embeddings_py/node_parser/relational/__init__.py
ipfs_embeddings_py/node_parser/relational/base_element.py
ipfs_embeddings_py/node_parser/relational/hierarchical.py
ipfs_embeddings_py/node_parser/relational/llama_parse_json_element.py
ipfs_embeddings_py/node_parser/relational/markdown_element.py
ipfs_embeddings_py/node_parser/relational/unstructured_element.py
ipfs_embeddings_py/node_parser/relational/utils.py
ipfs_embeddings_py/node_parser/text/__init__.py
ipfs_embeddings_py/node_parser/text/code.py
ipfs_embeddings_py/node_parser/text/langchain.py
ipfs_embeddings_py/node_parser/text/semantic_double_merging_splitter.py
ipfs_embeddings_py/node_parser/text/semantic_splitter.py
ipfs_embeddings_py/node_parser/text/sentence.py
ipfs_embeddings_py/node_parser/text/sentence_window.py
ipfs_embeddings_py/node_parser/text/token.py
ipfs_embeddings_py/node_parser/text/utils.py
ipfs_embeddings_py-0.0.28.dist-info/LICENSE
ipfs_embeddings_py-0.0.28.dist-info/LICENSE copy
ipfs_embeddings_py-0.0.28.dist-info/METADATA
ipfs_embeddings_py-0.0.28.dist-info/WHEEL
ipfs_embeddings_py-0.0.28.dist-info/top_level.txt
ipfs_embeddings_py-0.0.28.dist-info/RECORD
